bookmark_replace/__init__.py
bookmark_replace/cli.py
bookmark_replace-0.1.0.dist-info/licenses/LICENSE
bookmark_replace-0.1.0.dist-info/METADATA
bookmark_replace-0.1.0.dist-info/WHEEL
bookmark_replace-0.1.0.dist-info/entry_points.txt
bookmark_replace-0.1.0.dist-info/top_level.txt
bookmark_replace-0.1.0.dist-info/RECORD
