Metadata-Version: 2.4
Name: bookmark-replace
Version: 0.1.0
Summary: A tool to batch replace domains in bookmarks (HTML or Chrome JSON).
Author: EdgeLordKirito
License-Expression: MIT
Requires-Python: >=3.8
License-File: LICENSE
Dynamic: license-file
